<?xml version="1.0" encoding="UTF-8"?>
<TRANSFER xmlns="http://www.interlis.ch/INTERLIS2.3">
<HEADERSECTION SENDER="gisdaten-20230821" VERSION="2.3">
  <MODELS>
    <MODEL NAME="IliSite09" VERSION="2009-11-12" URI="mailto:ce@eisenhutinformatik.ch"/>
  </MODELS>
</HEADERSECTION>
<DATASECTION>
  <IliSite09.SiteMetadata  BID="NWOWb0">
    <IliSite09.SiteMetadata.Site  TID="1">
    <Name>models.gis-daten.ch/nw-ow</Name>
    <Title>Modell-Ablage GIS Daten AG</Title>
    <shortDescription>Modell-Ablage fuer Datenmodelle der GIS Daten AG</shortDescription>
    <Owner>http://www.gis-daten.ch</Owner>
    <technicalContact>mailto:support@gis-daten.ch</technicalContact>
    <parentSite>
      <IliSite09.RepositoryLocation_>
        <value>http://models.geo.kgk-cgc.ch/</value>
      </IliSite09.RepositoryLocation_>
    </parentSite>
    </IliSite09.SiteMetadata.Site>
  </IliSite09.SiteMetadata>
</DATASECTION>
</TRANSFER>

